llama.py
python_aiconfig_llama-0.0.1.dist-info/METADATA
python_aiconfig_llama-0.0.1.dist-info/WHEEL
python_aiconfig_llama-0.0.1.dist-info/top_level.txt
python_aiconfig_llama-0.0.1.dist-info/RECORD
