Metadata-Version: 2.1
Name: python-aiconfig-llama
Version: 0.0.1
Summary: LLama extension for AIConfig Library
Author-email: Jonathan Lessinger <jonathan@lastmileai.dev>
Project-URL: Homepage, https://github.com/lastmile-ai/aiconfig
Project-URL: Bug Tracker, https://github.com/lastmile-ai/aiconfig/issues
Classifier: Intended Audience :: Developers
Classifier: Programming Language :: Python :: 3
Requires-Python: >=3.7
Requires-Dist: llama-cpp-python
Requires-Dist: python-aiconfig
Requires-Dist: asyncio
